apkshadow/__init__.py
apkshadow/cli.py
apkshadow/cmdrunner.py
apkshadow/filters.py
apkshadow/globals.py
apkshadow/parser.py
apkshadow/utils.py
apkshadow/actions/__init__.py
apkshadow/actions/analyze.py
apkshadow/actions/decompile.py
apkshadow/actions/install.py
apkshadow/actions/list.py
apkshadow/actions/pull.py
apkshadow/analysis/__init__.py
apkshadow/analysis/collector.py
apkshadow/analysis/finding.py
apkshadow/analysis/renderer.py
apkshadow/analysis/manifestClasses/component.py
apkshadow/analysis/manifestClasses/manifestEntry.py
apkshadow/analysis/manifestClasses/permission.py
apkshadow/data/permissions.json
apkshadow-0.1.6.dist-info/licenses/LICENSE
apkshadow-0.1.6.dist-info/METADATA
apkshadow-0.1.6.dist-info/WHEEL
apkshadow-0.1.6.dist-info/entry_points.txt
apkshadow-0.1.6.dist-info/top_level.txt
apkshadow-0.1.6.dist-info/RECORD
