Metadata-Version: 2.4
Name: apkshadow
Version: 0.1.6
Summary: Android APK automation tool for bug bounty
Author: ISMAILSHADOW
License-Expression: MIT
Project-URL: Homepage, https://github.com/ISMAILGAMAL/apkshadow
License-File: LICENSE
Requires-Dist: tqdm
Dynamic: license-file
